ensembl_assembly/__init__.py
ensembl_assembly/_version.py
ensembl_assembly/ensembl_assembly.py
ensembl_assembly-0.0.5.dist-info/LICENSE
ensembl_assembly-0.0.5.dist-info/METADATA
ensembl_assembly-0.0.5.dist-info/WHEEL
ensembl_assembly-0.0.5.dist-info/top_level.txt
ensembl_assembly-0.0.5.dist-info/RECORD
