Metadata-Version: 2.1
Name: ensembl-assembly
Version: 0.0.5
Summary: Utility to search and download Ensembl data such as genome assemblies and gene annotations
Home-page: https://github.com/marco-mariotti/ensembl_assembly
Author: Marco Mariotti
Author-email: marco.mariotti@ub.edu
Classifier: Programming Language :: Python :: 3
Classifier: License :: OSI Approved :: MIT License
Classifier: Operating System :: OS Independent
Requires-Python: <3.10,>=3.6
License-File: LICENSE
Requires-Dist: more-itertools
Requires-Dist: easyterm (>=0.7.0)
Requires-Dist: pandas (>=1.2)
Requires-Dist: requests (>=2.27)
